{
  "dod": {
    "designTokens": true,
    "useThemedHook": true,
    "unitTests": true,
    "screenshotTests": false,
    "migration": false,
    "apiTable": false,
    "storybook": true,
    "pixsoView": true
  },
  "component": "AnchorLinks",
  "description": "В качестве основы используется AnchorLink из библиотеки Antd.",
  "usage": "Переключения в одном окне, между несколькими табами",
  "designLink": "https://pixso.net/app/design/_JQDYkYJW0yUZVsKeoSybw?icon_type=1&page-id=29963%3A101579",
  "pixsoView": "https://pixso.net/app/design/hD3Tb31jr4YLaPBf6JEN5Q"
}
