{
  "dod": {
    "designTokens": true,
    "useThemedHook": true,
    "unitTests": true,
    "screenshotTests": false,
    "migration": true,
    "apiTable": true,
    "storybook": true,
    "designLink": true,
    "pixsoView": true
  },
  "component": "Uploader",
  "description": "",
  "usage": "Компонент Uploader используется для загрузки файлов пользователями на платформу. Он позволяет выбрать один или несколько файлов вручную или перетаскиванием (drag and drop) в интерфейс. Upload автоматически проверяет размер, количество и формат файлов, чтобы соответствовать установленным ограничениям, и информирует пользователя о возникших ошибках",
  "designLink": "https://pixso.net/app/design/_JQDYkYJW0yUZVsKeoSybw?icon_type=1&page-id=2183%3A11211",
  "pixsoView": "https://pixso.net/app/design/85_ZxFQRnTdWU-6-KONSnA"
}
