{
  "component": "Dropdown",
  "v6": "/docs/atoms-dropdown--basic",
  "v3": [
    {
      "prop": "onVisibleChange",
      "changes": "Добавлен"
    },
    {
      "prop": "overlayClassName",
      "changes": "Добавлен"
    },
    {
      "prop": "trigger",
      "changes": "Добавлен триггер contextMenu, по нажатию на правую кнопку мыши"
    }
  ],
  "v5": [
    {
      "prop": "autoFocus",
      "changes": "Убран"
    },
    {
      "prop": "destroyPopupOnHide",
      "changes": "Убран"
    },
    {
      "prop": "getPopupContainer",
      "changes": "Убран"
    },
    {
      "prop": "overlayStyle",
      "changes": "Убран"
    }
  ],
  "common": []
}
