{
  "dod": {
    "designTokens": true,
    "useThemedHook": true,
    "unitTests": false,
    "screenshotTests": false,
    "migration": false,
    "apiTable": true,
    "storybook": true,
    "figmaView": true
  },
  "component": "Indicator",
  "description": "Компонент для цветовой индикации.",
  "usage": "",
  "designLink": "https://www.figma.com/file/9hiN2DbkqbxbhR9EWRI1VK/01-%5BB2B%5D-Hexa-UI-Components?type=design&node-id=50458%3A391378&mode=dev",
  "figmaView": "https://www.figma.com/embed?embed_host=share&url=https%3A%2F%2Fwww.figma.com%2Ffile%2F9hiN2DbkqbxbhR9EWRI1VK%2F01-%255BB2B%255D-Hexa-UI-Components%3Ftype%3Ddesign%26node-id%3D50458%253A391378%26mode%3Ddev"
}
