{
  "dod": {
    "designTokens": true,
    "useThemedHook": true,
    "unitTests": true,
    "screenshotTests": false,
    "migration": true,
    "apiTable": true,
    "storybook": true,
    "figmaView": true
  },
  "component": "Link",
  "description": "The component for rendering the link. The HTML Anchor element is used as the basis",
  "usage": "Indicates the ability to navigate to another page",
  "designLink": "https://www.figma.com/file/9hiN2DbkqbxbhR9EWRI1VK/B2B-Kit?node-id=1%3A2273",
  "figmaView": "https://www.figma.com/embed?embed_host=share&url=https%3A%2F%2Fwww.figma.com%2Ffile%2F9hiN2DbkqbxbhR9EWRI1VK%2FB2B-UI-KIT%3Fnode-id%3D33444%253A130132%26t%3D8p7kG6o1QctkHetZ-1"
}
