{
  "dod": {
    "designTokens": true,
    "useThemedHook": true,
    "unitTests": true,
    "screenshotTests": false,
    "migration": true,
    "apiTable": true,
    "storybook": true,
    "pixsoView": true
  },
  "component": "Link",
  "description": "Компонент для отрисовки ссылки. В качестве основы используется HTML элемент Anchor.",
  "usage": "Обозначает возможность перехода на другую страницу.",
  "designLink": "https://pixso.net/app/design/_JQDYkYJW0yUZVsKeoSybw?icon_type=1&page-id=33293%3A116703",
  "pixsoView": "https://pixso.net/app/design/KGurJC5_m7nSJTeVxB0zDg"
}
